mathpub
