Metadata-Version: 2.1
Name: mathpub
Version: 0.1.3
Summary: small library for quick formatting of math calculations
Author-email: timur20041229@gmail.com
Requires: IPython
Requires: ipywidgets
